<?xml version="1.0" encoding="UTF-8"?>
<!DOCTYPE plist PUBLIC "-//Apple//DTD PLIST 1.0//EN" "http://www.apple.com/DTDs/PropertyList-1.0.dtd"/>

<plist version="1.0">
    <dict>
        <key>ROOT</key>
        <array>
            <dict>
                <key>id</key>
                <string>105</string>
                <key>sprites</key>
                <array>
                    <string>106</string>
                </array>
            </dict>
            <dict>
                <key>id</key>
                <string>109</string>
                <key>sprites</key>
                <array>
                    <string>110</string>
                </array>
            </dict>
            <dict>
                <key>id</key>
                <string>120</string>
                <key>sprites</key>
                <array>
                    <string>121</string>
                </array>
            </dict>
            <dict>
                <key>id</key>
                <string>150</string>
                <key>sprites</key>
                <array>
                    <string>151</string>
                </array>
            </dict>
            <dict>
                <key>id</key>
                <string>341</string>
                <key>sprites</key>
                <array>
                    <string>342</string>
                </array>
            </dict>
            <dict>
                <key>id</key>
                <string>441</string>
                <key>sprites</key>
                <array>
                    <string>442</string>
                </array>
            </dict>
            <dict>
                <key>id</key>
                <string>991</string>
                <key>sprites</key>
                <array>
                    <string>992</string>
                </array>
            </dict>
            <dict>
                <key>id</key>
                <string>1042</string>
                <key>sprites</key>
                <array>
                    <string>1043</string>
                </array>
            </dict>
            <dict>
                <key>id</key>
                <string>1050</string>
                <key>sprites</key>
                <array>
                    <string>1051</string>
                </array>
            </dict>
            <dict>
                <key>id</key>
                <string>1186</string>
                <key>sprites</key>
                <array>
                    <string>1187</string>
                </array>
            </dict>
            <dict>
                <key>id</key>
                <string>1483</string>
                <key>sprites</key>
                <array>
                    <string>1484</string>
                </array>
            </dict>
            <dict>
                <key>id</key>
                <string>1489</string>
                <key>sprites</key>
                <array>
                    <string>1490</string>
                </array>
            </dict>
            <dict>
                <key>id</key>
                <string>1501</string>
                <key>sprites</key>
                <array>
                    <string>1502</string>
                </array>
            </dict>
            <dict>
                <key>id</key>
                <string>1566</string>
                <key>sprites</key>
                <array>
                    <string>1567</string>
                </array>
            </dict>
            <dict>
                <key>id</key>
                <string>1572</string>
                <key>sprites</key>
                <array>
                    <string>1573</string>
                </array>
            </dict>
            <dict>
                <key>id</key>
                <string>1575</string>
                <key>sprites</key>
                <array>
                    <string>1576</string>
                </array>
            </dict>
            <dict>
                <key>id</key>
                <string>1580</string>
                <key>sprites</key>
                <array>
                    <string>1581</string>
                </array>
            </dict>
            <dict>
                <key>id</key>
                <string>1588</string>
                <key>sprites</key>
                <array>
                    <string>1589</string>
                </array>
            </dict>
            <dict>
                <key>id</key>
                <string>1590</string>
                <key>sprites</key>
                <array>
                    <string>1591</string>
                </array>
            </dict>
            <dict>
                <key>id</key>
                <string>1597</string>
                <key>sprites</key>
                <array>
                    <string>1598</string>
                </array>
            </dict>
            <dict>
                <key>id</key>
                <string>1603</string>
                <key>sprites</key>
                <array>
                    <string>1604</string>
                </array>
            </dict>
            <dict>
                <key>id</key>
                <string>1609</string>
                <key>sprites</key>
                <array>
                    <string>1610</string>
                </array>
            </dict>
            <dict>
                <key>id</key>
                <string>1612</string>
                <key>sprites</key>
                <array>
                    <string>1613</string>
                </array>
            </dict>
            <dict>
                <key>id</key>
                <string>1615</string>
                <key>sprites</key>
                <array>
                    <string>1616</string>
                </array>
            </dict>
            <dict>
                <key>id</key>
                <string>1618</string>
                <key>sprites</key>
                <array>
                    <string>1619</string>
                </array>
            </dict>
            <dict>
                <key>id</key>
                <string>1625</string>
                <key>sprites</key>
                <array>
                    <string>1626</string>
                </array>
            </dict>
            <dict>
                <key>id</key>
                <string>1628</string>
                <key>sprites</key>
                <array>
                    <string>1629</string>
                </array>
            </dict>
            <dict>
                <key>id</key>
                <string>1659</string>
                <key>sprites</key>
                <array>
                    <string>1660</string>
                </array>
            </dict>
            <dict>
                <key>id</key>
                <string>1662</string>
                <key>sprites</key>
                <array>
                    <string>1663</string>
                </array>
            </dict>
            <dict>
                <key>id</key>
                <string>1680</string>
                <key>sprites</key>
                <array>
                    <string>1681</string>
                </array>
            </dict>
            <dict>
                <key>id</key>
                <string>1684</string>
                <key>sprites</key>
                <array>
                    <string>1685</string>
                </array>
            </dict>
            <dict>
                <key>id</key>
                <string>1711</string>
                <key>sprites</key>
                <array>
                    <string>1712</string>
                </array>
            </dict>
            <dict>
                <key>id</key>
                <string>1722</string>
                <key>sprites</key>
                <array>
                    <string>1723</string>
                </array>
            </dict>
            <dict>
                <key>id</key>
                <string>1735</string>
                <key>sprites</key>
                <array>
                    <string>1736</string>
                </array>
            </dict>
            <dict>
                <key>id</key>
                <string>1774</string>
                <key>sprites</key>
                <array>
                    <string>1775</string>
                </array>
            </dict>
            <dict>
                <key>id</key>
                <string>1804</string>
                <key>sprites</key>
                <array>
                    <string>1805</string>
                    <string>1806</string>
                    <string>1807</string>
                    <string>1808</string>
                    <string>1809</string>
                    <string>1810</string>
                    <string>1811</string>
                    <string>1812</string>
                    <string>1813</string>
                    <string>1814</string>
                </array>
            </dict>
            <dict>
                <key>id</key>
                <string>1825</string>
                <key>sprites</key>
                <array>
                    <string>1826</string>
                </array>
            </dict>
            <dict>
                <key>id</key>
                <string>1833</string>
                <key>sprites</key>
                <array>
                    <string>1834</string>
                </array>
            </dict>
            <dict>
                <key>id</key>
                <string>1853</string>
                <key>sprites</key>
                <array>
                    <string>1854</string>
                </array>
            </dict>
            <dict>
                <key>id</key>
                <string>1887</string>
                <key>sprites</key>
                <array>
                    <string>1888</string>
                    <string>1889</string>
                    <string>1890</string>
                    <string>1891</string>
                    <string>1892</string>
                    <string>1893</string>
                    <string>1894</string>
                    <string>1895</string>
                    <string>1896</string>
                    <string>1897</string>
                </array>
            </dict>
            <dict>
                <key>id</key>
                <string>1914</string>
                <key>sprites</key>
                <array>
                    <string>1915</string>
                </array>
            </dict>
            <dict>
                <key>id</key>
                <string>1922</string>
                <key>sprites</key>
                <array>
                    <string>1923</string>
                </array>
            </dict>
            <dict>
                <key>id</key>
                <string>1931</string>
                <key>sprites</key>
                <array>
                    <string>1932</string>
                </array>
            </dict>
            <dict>
                <key>id</key>
                <string>1939</string>
                <key>sprites</key>
                <array>
                    <string>1940</string>
                </array>
            </dict>
            <dict>
                <key>id</key>
                <string>1947</string>
                <key>sprites</key>
                <array>
                    <string>1948</string>
                </array>
            </dict>
            <dict>
                <key>id</key>
                <string>2023</string>
                <key>sprites</key>
                <array>
                    <string>2024</string>
                </array>
            </dict>
            <dict>
                <key>id</key>
                <string>2050</string>
                <key>sprites</key>
                <array>
                    <string>2051</string>
                </array>
            </dict>
            <dict>
                <key>id</key>
                <string>2222</string>
                <key>sprites</key>
                <array>
                    <string>2223</string>
                </array>
            </dict>
            <dict>
                <key>id</key>
                <string>2233</string>
                <key>sprites</key>
                <array>
                    <string>2234</string>
                    <string>2235</string>
                    <string>2236</string>
                    <string>2237</string>
                    <string>2238</string>
                    <string>2239</string>
                    <string>2240</string>
                    <string>2241</string>
                    <string>2242</string>
                    <string>2243</string>
                </array>
            </dict>
            <dict>
                <key>id</key>
                <string>2671</string>
                <key>sprites</key>
                <array>
                    <string>2672</string>
                </array>
            </dict>
            <dict>
                <key>id</key>
                <string>2729</string>
                <key>sprites</key>
                <array>
                    <string>2730</string>
                </array>
            </dict>
            <dict>
                <key>id</key>
                <string>2903</string>
                <key>sprites</key>
                <array>
                    <string>2904</string>
                    <string>2905</string>
                    <string>2906</string>
                    <string>2907</string>
                    <string>2908</string>
                    <string>2909</string>
                    <string>2910</string>
                    <string>2911</string>
                    <string>2912</string>
                    <string>2913</string>
                    <string>2914</string>
                    <string>2915</string>
                    <string>2916</string>
                    <string>2917</string>
                    <string>2918</string>
                    <string>2919</string>
                    <string>2920</string>
                </array>
            </dict>
            <dict>
                <key>id</key>
                <string>3229</string>
                <key>sprites</key>
                <array>
                    <string>3230</string>
                    <string>3231</string>
                    <string>3232</string>
                    <string>3234</string>
                    <string>3235</string>
                    <string>3236</string>
                    <string>3237</string>
                    <string>3238</string>
                    <string>3239</string>
                    <string>3240</string>
                </array>
            </dict>
            <dict>
                <key>id</key>
                <string>3253</string>
                <key>sprites</key>
                <array>
                    <string>3254</string>
                    <string>3255</string>
                    <string>3256</string>
                    <string>3257</string>
                    <string>3258</string>
                    <string>3259</string>
                    <string>3260</string>
                    <string>3261</string>
                    <string>3262</string>
                    <string>3263</string>
                </array>
            </dict>
            <dict>
                <key>id</key>
                <string>4220</string>
                <key>sprites</key>
                <array>
                    <string>4221</string>
                    <string>4222</string>
                </array>
            </dict>
        </array>
    </dict>
</plist>
